xueqiu_funds/__init__.py
xueqiu_funds/client.py
xueqiu_funds/middleware/__init__.py
xueqiu_funds/middleware/fund_detail.py
xueqiu_funds/middleware/fund_intro.py
xueqiu_funds-0.0.3.dist-info/LICENSE
xueqiu_funds-0.0.3.dist-info/METADATA
xueqiu_funds-0.0.3.dist-info/WHEEL
xueqiu_funds-0.0.3.dist-info/RECORD
